FAdo/__init__.py
FAdo/automata_grammar.lark
FAdo/cfg.py
FAdo/codes.py
FAdo/comboperations.py
FAdo/common.py
FAdo/conversions.py
FAdo/fa.py
FAdo/families.py
FAdo/fio.py
FAdo/fl.py
FAdo/graphs.py
FAdo/prax.py
FAdo/reex.py
FAdo/regexp_grammar.lark
FAdo/rndadfa.py
FAdo/rndfap.py
FAdo/ska.py
FAdo/smwc.py
FAdo/ssemigroup.py
FAdo/sst.py
FAdo/tfa.py
FAdo/transducers.py
FAdo/unionFind.py
FAdo/witness.py
fado-2.1.2.dist-info/METADATA
fado-2.1.2.dist-info/WHEEL
fado-2.1.2.dist-info/RECORD
