Metadata-Version: 2.1
Name: fado
Version: 2.1.2
Summary: A library of tools to manipulate formal languages' representations  mainly automata and regular expressions.
Home-page: https://fado.dcc.fc.up.pt
License: GPL-3.0-or-later
Keywords: automata theory,formal languages,regular expressions,transducers
Author: Rogerio Reis
Author-email: rogerio.reis@fc.up.pt
Requires-Python: >=3.10,<4.0
Classifier: License :: OSI Approved :: GNU General Public License v3 or later (GPLv3+)
Classifier: Programming Language :: Python :: 3
Classifier: Programming Language :: Python :: 3.10
Classifier: Programming Language :: Python :: 3.11
Requires-Dist: argparse (>=1.4.0,<2.0.0)
Requires-Dist: black (>=22.1.0,<23.0.0)
Requires-Dist: deprecation (>=2.1.0,<3.0.0)
Requires-Dist: graphviz (>=0.19.1,<0.20.0)
Requires-Dist: ipython (>=7.0.0,<8.0.0)
Requires-Dist: jupyter (>=1.0.0,<2.0.0)
Requires-Dist: lark (>=1.1.5,<2.0.0)
Requires-Dist: mistune (>=2.0.2,<3.0.0)
Requires-Dist: networkx (>=2.6.3,<3.0.0)
Requires-Dist: platformdirs (>=2.5.0,<3.0.0)
Requires-Dist: prompt-toolkit (>=3.0.27,<4.0.0)
Requires-Dist: tomli (>=2.0.1,<3.0.0)
Project-URL: Documentation, https://www.dcc.fc.up.pt/~rvr/FAdoDoc
